MANIFEST.in
README.md
setup.py
pydcd/__init__.py
pydcd/dcd.py
pydcd/dcd_model.py
pydcd/generate_random_networks.py
pydcd/kmeans.py
pydcd/load_data.py
pydcd/load_package_data.py
pydcd/modularity_maximization.py
pydcd.egg-info/PKG-INFO
pydcd.egg-info/SOURCES.txt
pydcd.egg-info/dependency_links.txt
pydcd.egg-info/requires.txt
pydcd.egg-info/top_level.txt
pydcd/data/citation_edges.txt
pydcd/data/citation_nodes.txt
pydcd/data/fb_edges.txt
pydcd/data/fb_node_withattributes.txt
pydcd/data/fb_nodes_noattributes.txt