Metadata-Version: 2.1
Name: pydcd
Version: 0.0.13
Summary: PyDCD: A Deep Learning-Based Community Detection Software in Python for Large-scale Networks
Home-page: https://github.com/kpzhang/deepcommunitydetection
Author: Kunpeng Zhang & Shaokun Fan & Bruce Golden
Author-email: shaokunfan@gmail.com
License: UNKNOWN
Platform: UNKNOWN
Classifier: Programming Language :: Python :: 3
Classifier: License :: OSI Approved :: MIT License
Classifier: Operating System :: OS Independent
Requires-Python: >=3.1
